bgg_pi/__init__.py
bgg_pi/client.py
bgg_pi/const.py
bgg_pi/exceptions.py
bgg_pi-0.1.1.dist-info/METADATA
bgg_pi-0.1.1.dist-info/WHEEL
bgg_pi-0.1.1.dist-info/licenses/LICENSE
bgg_pi-0.1.1.dist-info/RECORD
