Metadata-Version: 2.4
Name: bgg-pi
Version: 0.1.1
Summary: A modern, async python client for BoardGameGeek.
Project-URL: Homepage, https://github.com/seanmccabe/bgg-pi
Author-email: Sean McCabe <sean@example.com>
License-File: LICENSE
Classifier: Development Status :: 4 - Beta
Classifier: License :: OSI Approved :: MIT License
Classifier: Operating System :: OS Independent
Classifier: Programming Language :: Python :: 3
Classifier: Programming Language :: Python :: 3.11
Classifier: Programming Language :: Python :: 3.12
Requires-Python: >=3.11
Requires-Dist: aiohttp>=3.9.0
